dirty_models/__init__.py
dirty_models/base.py
dirty_models/fields.py
dirty_models/model_types.py
dirty_models/models.py
dirty_models/utils.py
dirty_models-0.12.4.dist-info/LICENSE
dirty_models-0.12.4.dist-info/METADATA
dirty_models-0.12.4.dist-info/WHEEL
dirty_models-0.12.4.dist-info/top_level.txt
dirty_models-0.12.4.dist-info/zip-safe
dirty_models-0.12.4.dist-info/RECORD
