Metadata-Version: 2.1
Name: dirty-models
Version: 0.12.4
Summary: Dirty models for python 3
Home-page: https://github.com/alfred82santa/dirty-models
Author: alfred82santa
Author-email: alfred82santa@gmail.com
License: BSD
Platform: UNKNOWN
Classifier: Intended Audience :: Developers
Classifier: Programming Language :: Python
Classifier: Programming Language :: Python :: 3.3
Classifier: Programming Language :: Python :: 3.4
Classifier: Programming Language :: Python :: 3.5
Classifier: Programming Language :: Python :: 3.6
Classifier: License :: OSI Approved :: BSD License
Classifier: Development Status :: 4 - Beta
License-File: LICENSE
Requires-Dist: python-dateutil
